aa_rss_to_discord/__init__.py
aa_rss_to_discord/admin.py
aa_rss_to_discord/apps.py
aa_rss_to_discord/auth_hooks.py
aa_rss_to_discord/constants.py
aa_rss_to_discord/managers.py
aa_rss_to_discord/models.py
aa_rss_to_discord/providers.py
aa_rss_to_discord/tasks.py
aa_rss_to_discord/discordbot/cogs/__init__.py
aa_rss_to_discord/discordbot/cogs/rss.py
aa_rss_to_discord/locale/django.pot
aa_rss_to_discord/locale/cs_CZ/LC_MESSAGES/django.mo
aa_rss_to_discord/locale/cs_CZ/LC_MESSAGES/django.po
aa_rss_to_discord/locale/de/LC_MESSAGES/django.mo
aa_rss_to_discord/locale/de/LC_MESSAGES/django.po
aa_rss_to_discord/locale/es/LC_MESSAGES/django.mo
aa_rss_to_discord/locale/es/LC_MESSAGES/django.po
aa_rss_to_discord/locale/fr_FR/LC_MESSAGES/django.mo
aa_rss_to_discord/locale/fr_FR/LC_MESSAGES/django.po
aa_rss_to_discord/locale/it_IT/LC_MESSAGES/django.mo
aa_rss_to_discord/locale/it_IT/LC_MESSAGES/django.po
aa_rss_to_discord/locale/ja/LC_MESSAGES/django.mo
aa_rss_to_discord/locale/ja/LC_MESSAGES/django.po
aa_rss_to_discord/locale/ko_KR/LC_MESSAGES/django.mo
aa_rss_to_discord/locale/ko_KR/LC_MESSAGES/django.po
aa_rss_to_discord/locale/nl_NL/LC_MESSAGES/django.mo
aa_rss_to_discord/locale/nl_NL/LC_MESSAGES/django.po
aa_rss_to_discord/locale/pl_PL/LC_MESSAGES/django.mo
aa_rss_to_discord/locale/pl_PL/LC_MESSAGES/django.po
aa_rss_to_discord/locale/ru/LC_MESSAGES/django.mo
aa_rss_to_discord/locale/ru/LC_MESSAGES/django.po
aa_rss_to_discord/locale/sk/LC_MESSAGES/django.mo
aa_rss_to_discord/locale/sk/LC_MESSAGES/django.po
aa_rss_to_discord/locale/uk/LC_MESSAGES/django.mo
aa_rss_to_discord/locale/uk/LC_MESSAGES/django.po
aa_rss_to_discord/locale/zh_Hans/LC_MESSAGES/django.mo
aa_rss_to_discord/locale/zh_Hans/LC_MESSAGES/django.po
aa_rss_to_discord/migrations/0001_initial.py
aa_rss_to_discord/migrations/0002_enable_disable_rss_feeds.py
aa_rss_to_discord/migrations/__init__.py
aa_rss_to_discord/tests/__init__.py
aa_rss_to_discord/tests/test_auth_hooks.py
aa_rss_to_discord/tests/test_managers.py
aa_rss_to_discord-2.5.0.dist-info/METADATA
aa_rss_to_discord-2.5.0.dist-info/WHEEL
aa_rss_to_discord-2.5.0.dist-info/licenses/LICENSE
aa_rss_to_discord-2.5.0.dist-info/RECORD
